rtt_console/__init__.py
rtt_console/console.py
rtt_console/default_command.py
rtt_console/jlink_dongle.py
rtt_console/version.py
rtt_console-0.2.8.dist-info/LICENSE
rtt_console-0.2.8.dist-info/METADATA
rtt_console-0.2.8.dist-info/WHEEL
rtt_console-0.2.8.dist-info/entry_points.txt
rtt_console-0.2.8.dist-info/top_level.txt
rtt_console-0.2.8.dist-info/RECORD
