Metadata-Version: 2.1
Name: rtt_console
Version: 0.2.8
Summary: Simple Segger RTT console.
Home-page: https://github.com/Mcublog/rtt-console
Author: Viacheslav
Author-email: viacheslav@mcublog.xyz
Classifier: Programming Language :: Python :: 3
Classifier: License :: OSI Approved :: MIT License
Classifier: Operating System :: OS Independent
Requires-Python: >=3.8
License-File: LICENSE
Requires-Dist: pylink-square==0.13.0
Requires-Dist: prompt-toolkit==3.0.29
Requires-Dist: colorama==0.4.4
Requires-Dist: psutil==5.9.1
